alu.v
`default_nettype none

module alu (
    input      [31:0] a,
    input      [31:0] b,
    input      [4:0]  alu_op,
    output reg [31:0] result,
    output reg        zero_flag
);

    // ALU Operation Codes
    parameter ALU_ADD  = 5'b00000;
    parameter ALU_SUB  = 5'b00001;
    parameter ALU_SLL  = 5'b00010;
    parameter ALU_SLT  = 5'b00011;
    parameter ALU_SLTU = 5'b00100;
    parameter ALU_XOR  = 5'b00101;
    parameter ALU_SRL  = 5'b00110;
    parameter ALU_SRA  = 5'b00111;
    parameter ALU_OR   = 5'b01000;
    parameter ALU_AND  = 5'b01001;

    always @(*) begin
        case (alu_op)
            ALU_ADD:  result = a + b;
            ALU_SUB:  result = a - b;
            ALU_SLL:  result = a << b[4:0];
            ALU_SLT:  result = ($signed(a) < $signed(b)) ? 32'd1 : 32'd0;
            ALU_SLTU: result = (a < b) ? 32'd1 : 32'd0;
            ALU_XOR:  result = a ^ b;
            ALU_SRL:  result = a >> b[4:0];
            ALU_SRA:  result = $signed(a) >>> b[4:0];
            ALU_OR:   result = a | b;
            ALU_AND:  result = a & b;
            default:  result = 32'hdeadbeef; // Should not happen
        endcase

        zero_flag = (result == 32'd0);
    end

endmodule

imm_gen.v
`default_nettype none

module imm_gen (
    input      [31:0] inst,
    input      [2:0]  imm_type_sel,
    output reg [31:0] imm
);

    parameter IMM_I_TYPE = 3'b000;
    parameter IMM_S_TYPE = 3'b001;
    parameter IMM_B_TYPE = 3'b010;
    parameter IMM_U_TYPE = 3'b011;
    parameter IMM_J_TYPE = 3'b100;

    always @(*) begin
        case (imm_type_sel)
            IMM_I_TYPE: imm = {{20{inst[31]}}, inst[31:20]};
            IMM_S_TYPE: imm = {{20{inst[31]}}, inst[31:25], inst[11:7]};
            IMM_B_TYPE: imm = {{19{inst[31]}}, inst[31], inst[7], inst[30:25], inst[11:8], 1'b0};
            IMM_U_TYPE: imm = {inst[31:12], 12'b0};
            IMM_J_TYPE: imm = {{12{inst[31]}}, inst[19:12], inst[20], inst[30:21], 1'b0};
            default: imm = 32'hdeadbeef; // Should not happen
        endcase
    end

endmodule

reg_file.v
`default_nettype none

module reg_file (
    input         clk,
    input         write_enable,
    input  [4:0]  rs1_addr,
    input  [4:0]  rs2_addr,
    input  [4:0]  rd_addr,
    input  [31:0] write_data,
    output [31:0] rs1_data,
    output [31:0] rs2_data
);

    reg [31:0] registers[0:31];

    // Two asynchronous read ports
    assign rs1_data = (rs1_addr == 5'b0) ? 32'b0 : registers[rs1_addr];
    assign rs2_data = (rs2_addr == 5'b0) ? 32'b0 : registers[rs2_addr];

    // One synchronous write port
    always @(posedge clk) begin
        if (write_enable && (rd_addr != 5'b0)) begin
            registers[rd_addr] <= write_data;
        end
    end

    // Initialize registers to 0 for simulation
    integer i;
    initial begin
        for (i = 0; i < 32; i = i + 1) begin
            registers[i] = 32'b0;
        end
    end

endmodule

control_unit.v
`default_nettype none

module control_unit (
    input      [6:0]  opcode,
    input      [2:0]  funct3,
    input      [6:0]  funct7,
    input             zero_flag,
    input             alu_lt_flag, // Assuming this comes from ALU result[0]

    output reg [4:0]  alu_op,
    output reg        alu_src_a_sel,
    output reg        alu_src_b_sel,
    output reg        reg_write_en,
    output reg [1:0]  mem_to_reg_sel,
    output reg        mem_read_en,
    output reg        mem_write_en,
    output reg        branch_cond,
    output reg [2:0]  imm_type_sel,
    output reg        jal_op,
    output reg        jalr_op
);

    // Opcodes
    parameter R_TYPE   = 7'b0110011;
    parameter I_TYPE_A = 7'b0010011; // Arith/Logic
    parameter I_TYPE_L = 7'b0000011; // Load
    parameter I_TYPE_J = 7'b1100111; // JALR
    parameter S_TYPE   = 7'b0100011;
    parameter B_TYPE   = 7'b1100011;
    parameter LUI      = 7'b0110111;
    parameter AUIPC    = 7'b0010111;
    parameter JAL      = 7'b1101111;

    // ALU operations from alu.v
    parameter ALU_ADD  = 5'b00000;
    parameter ALU_SUB  = 5'b00001;
    parameter ALU_SLL  = 5'b00010;
    parameter ALU_SLT  = 5'b00011;
    parameter ALU_SLTU = 5'b00100;
    parameter ALU_XOR  = 5'b00101;
    parameter ALU_SRL  = 5'b00110;
    parameter ALU_SRA  = 5'b00111;
    parameter ALU_OR   = 5'b01000;
    parameter ALU_AND  = 5'b01001;

    // Immediate types from imm_gen.v
    parameter IMM_I_TYPE = 3'b000;
    parameter IMM_S_TYPE = 3'b001;
    parameter IMM_B_TYPE = 3'b010;
    parameter IMM_U_TYPE = 3'b011;
    parameter IMM_J_TYPE = 3'b100;

    // Control Signal values
    parameter PC_SEL = 1'b1;
    parameter RS1_SEL = 1'b0;

    parameter IMM_SEL = 1'b1;
    parameter RS2_SEL = 1'b0;

    parameter MTR_ALU_RES = 2'b00;
    parameter MTR_MEM_DATA = 2'b01;
    parameter MTR_PC_4 = 2'b10;


    always @(*) begin
        // Default values
        alu_op = ALU_ADD;
        alu_src_a_sel = RS1_SEL;
        alu_src_b_sel = RS2_SEL;
        reg_write_en = 1'b0;
        mem_to_reg_sel = MTR_ALU_RES;
        mem_read_en = 1'b0;
        mem_write_en = 1'b0;
        branch_cond = 1'b0;
        imm_type_sel = IMM_I_TYPE;
        jal_op = 1'b0;
        jalr_op = 1'b0;

        case (opcode)
            R_TYPE: begin
                reg_write_en = 1'b1;
                case (funct3)
                    3'b000: alu_op = (funct7 == 7'b0100000) ? ALU_SUB : ALU_ADD;
                    3'b001: alu_op = ALU_SLL;
                    3'b010: alu_op = ALU_SLT;
                    3'b011: alu_op = ALU_SLTU;
                    3'b100: alu_op = ALU_XOR;
                    3'b101: alu_op = (funct7 == 7'b0100000) ? ALU_SRA : ALU_SRL;
                    3'b110: alu_op = ALU_OR;
                    3'b111: alu_op = ALU_AND;
                endcase
            end
            I_TYPE_A: begin
                reg_write_en = 1'b1;
                alu_src_b_sel = IMM_SEL;
                imm_type_sel = IMM_I_TYPE;
                case (funct3)
                    3'b000: alu_op = ALU_ADD;
                    3'b001: alu_op = ALU_SLL;
                    3'b010: alu_op = ALU_SLT;
                    3'b011: alu_op = ALU_SLTU;
                    3'b100: alu_op = ALU_XOR;
                    3'b101: alu_op = (funct7 == 7'b0100000) ? ALU_SRA : ALU_SRL;
                    3'b110: alu_op = ALU_OR;
                    3'b111: alu_op = ALU_AND;
                endcase
            end
            I_TYPE_L: begin
                reg_write_en = 1'b1;
                mem_read_en = 1'b1;
                alu_src_b_sel = IMM_SEL;
                mem_to_reg_sel = MTR_MEM_DATA;
                imm_type_sel = IMM_I_TYPE;
                alu_op = ALU_ADD;
            end
            I_TYPE_J: begin // JALR
                jalr_op = 1'b1;
                reg_write_en = 1'b1;
                mem_to_reg_sel = MTR_PC_4;
                imm_type_sel = IMM_I_TYPE;
                alu_op = ALU_ADD; // Will be used to calculate target address
            end
            S_TYPE: begin
                mem_write_en = 1'b1;
                alu_src_b_sel = IMM_SEL;
                imm_type_sel = IMM_S_TYPE;
                alu_op = ALU_ADD;
            end
            B_TYPE: begin
                imm_type_sel = IMM_B_TYPE;
                case (funct3)
                    3'b000: branch_cond = zero_flag;       // BEQ
                    3'b001: branch_cond = ~zero_flag;      // BNE
                    3'b100: branch_cond = alu_lt_flag;     // BLT
                    3'b101: branch_cond = ~alu_lt_flag;    // BGE
                    3'b110: branch_cond = alu_lt_flag;     // BLTU
                    3'b111: branch_cond = ~alu_lt_flag;    // BGEU
                endcase;
                 case (funct3)
                    3'b000, 3'b001: alu_op = ALU_SUB; // For BEQ, BNE
                    3'b100, 3'b101: alu_op = ALU_SLT; // For BLT, BGE
                    3'b110, 3'b111: alu_op = ALU_SLTU; // For BLTU, BGEU
                endcase
            end
            LUI: begin
                reg_write_en = 1'b1;
                alu_src_a_sel = RS1_SEL; //rs1 should be 0 for LUI
                alu_src_b_sel = IMM_SEL; 
                imm_type_sel = IMM_U_TYPE;
                alu_op = ALU_ADD; 
            end
            AUIPC: begin
                reg_write_en = 1'b1;
                alu_src_a_sel = PC_SEL;
                alu_src_b_sel = IMM_SEL;
                imm_type_sel = IMM_U_TYPE;
                alu_op = ALU_ADD;
            end
            JAL: begin
                jal_op = 1'b1;
                reg_write_en = 1'b1;
                mem_to_reg_sel = MTR_PC_4;
                imm_type_sel = IMM_J_TYPE;
                // This will need to be handled in PC logic
            end
        endcase
    end

endmodule

pc_logic.v
`default_nettype none

module pc_logic (
    input         clk,
    input         reset,
    input         branch_cond,
    input         jal_op,
    input         jalr_op,
    input  [31:0] imm,
    input  [31:0] rs1_data,
    output reg [31:0] pc
);

    reg [31:0] next_pc;

    always @(*) begin
        if (jalr_op) begin
            next_pc = (rs1_data + imm) & 32'hfffffffe; // JALR
        end else if (jal_op) begin
            next_pc = pc + imm; // JAL
        end else if (branch_cond) begin
            next_pc = pc + imm; // Branch
        end else begin
            next_pc = pc + 4; // Default
        end
    end

    always @(posedge clk) begin
        if (reset) begin
            pc <= 32'h00000000;
        end else begin
            pc <= next_pc;
        end
    end

endmodule

riscv_processor.v
`default_nettype none

module riscv_processor (
    input clk,
    input reset,

    // Memory Interface
    output [31:0] mem_addr,
    output [31:0] mem_wdata,
    output [3:0]  mem_wmask,
    output        mem_rstrb,
    input  [31:0] mem_rdata,
    input         mem_rbusy,
    input         mem_wbusy
);

    // PC and Instruction
    wire [31:0] pc;
    wire [31:0] inst;

    // Control Unit signals
    wire [4:0]  alu_op;
    wire        alu_src_a_sel;
    wire        alu_src_b_sel;
    wire        reg_write_en;
    wire [1:0]  mem_to_reg_sel;
    wire        mem_read_en;
    wire        mem_write_en;
    wire        branch_cond;
    wire [2:0]  imm_type_sel;
    wire        jal_op;
    wire        jalr_op;

    // Imm Gen
    wire [31:0] imm;

    // Reg File
    wire [31:0] rs1_data;
    wire [31:0] rs2_data;
    wire [31:0] reg_write_data;

    // ALU
    wire [31:0] alu_a;
    wire [31:0] alu_b;
    wire [31:0] alu_result;
    wire        alu_zero_flag;
    wire        alu_lt_flag = alu_result[0];

    // Datapath
    assign inst = mem_rdata;

    pc_logic pc_logic_inst (
        .clk(clk),
        .reset(reset),
        .branch_cond(branch_cond),
        .jal_op(jal_op),
        .jalr_op(jalr_op),
        .imm(imm),
        .rs1_data(rs1_data),
        .pc(pc)
    );

    control_unit cu_inst (
        .opcode(inst[6:0]),
        .funct3(inst[14:12]),
        .funct7(inst[31:25]),
        .zero_flag(alu_zero_flag),
        .alu_lt_flag(alu_lt_flag),
        .alu_op(alu_op),
        .alu_src_a_sel(alu_src_a_sel),
        .alu_src_b_sel(alu_src_b_sel),
        .reg_write_en(reg_write_en),
        .mem_to_reg_sel(mem_to_reg_sel),
        .mem_read_en(mem_read_en),
        .mem_write_en(mem_write_en),
        .branch_cond(branch_cond),
        .imm_type_sel(imm_type_sel),
        .jal_op(jal_op),
        .jalr_op(jalr_op)
    );

    reg_file rf_inst (
        .clk(clk),
        .write_enable(reg_write_en),
        .rs1_addr(inst[19:15]),
        .rs2_addr(inst[24:20]),
        .rd_addr(inst[11:7]),
        .write_data(reg_write_data),
        .rs1_data(rs1_data),
        .rs2_data(rs2_data)
    );

    imm_gen ig_inst (
        .inst(inst),
        .imm_type_sel(imm_type_sel),
        .imm(imm)
    );

    assign alu_a = alu_src_a_sel ? pc : rs1_data;
    assign alu_b = alu_src_b_sel ? imm : rs2_data;

    alu alu_inst (
        .a(alu_a),
        .b(alu_b),
        .alu_op(alu_op),
        .result(alu_result),
        .zero_flag(alu_zero_flag)
    );

    // Memory Interface
    assign mem_addr = (mem_read_en | mem_write_en) ? alu_result : pc;
    assign mem_rstrb = ~mem_write_en; 
    assign mem_wdata = rs2_data;
    
    reg [3:0] wmask;
    always@(*) begin
        if(mem_write_en) begin
            case(inst[14:12]) //funct3
                 3'b000: wmask = 4'b1 << alu_result[1:0]; //SB
                 3'b001: wmask = 4'b11 << alu_result[1:0]; //SH
                 3'b010: wmask = 4'b1111; //SW
                 default: wmask = 4'b0;
            endcase
        end else begin
            wmask = 4'b0;
        end
    end
    assign mem_wmask = wmask;

    // Write Back
    reg [31:0] load_data_extended;
    always @(*) begin
        if (mem_read_en) begin
            case (inst[14:12]) // funct3 for loads
                3'b000: load_data_extended = {{24{mem_rdata[7]}}, mem_rdata[7:0]};   // LB
                3'b001: load_data_extended = {{16{mem_rdata[15]}}, mem_rdata[15:0]}; // LH
                3'b010: load_data_extended = mem_rdata;                            // LW
                3'b100: load_data_extended = {24'b0, mem_rdata[7:0]};               // LBU
                3'b101: load_data_extended = {16'b0, mem_rdata[15:0]};             // LHU
                default: load_data_extended = mem_rdata;
            endcase
        end else begin
            load_data_extended = 32'hdeadbeef;
        end
    end

    // mem_to_reg_sel: 00: ALU, 01: Mem, 10: PC+4
    assign reg_write_data = (mem_to_reg_sel == 2'b01) ? load_data_extended :
                            (mem_to_reg_sel == 2'b10) ? pc + 4 :
                            alu_result;

endmodule

riscv_testbench.v
`default_nettype none
`timescale 1ns/1ps

module riscv_testbench;

    reg clk;
    reg reset;

    wire [31:0] mem_addr;
    wire [31:0] mem_wdata;
    wire [3:0]  mem_wmask;
    wire        mem_rstrb;
    reg  [31:0] mem_rdata;

    // Instantiate the processor
    riscv_processor dut (
        .clk(clk),
        .reset(reset),
        .mem_addr(mem_addr),
        .mem_wdata(mem_wdata),
        .mem_wmask(mem_wmask),
        .mem_rstrb(mem_rstrb),
        .mem_rdata(mem_rdata)
    );

    // Clock generation
    always #5 clk = ~clk;

    // Simple memory model
    reg [31:0] memory[0:1023];

    always @(posedge clk) begin
        if (mem_rstrb) begin
            mem_rdata <= memory[mem_addr >> 2];
        end
        if (|mem_wmask) begin
            // Simplified write, does not handle mask
            memory[mem_addr >> 2] <= mem_wdata;
        end
    end

    // Test sequence
    initial begin
        clk = 0;
        reset = 1;
        #10;
        reset = 0;
        #100;
        $finish;
    end

    // Waveform dump
    initial begin
        $dumpfile("simulation.vcd");
        $dumpvars(0, riscv_testbench);
    end

endmodule

simulation.vcd
$date
	Thu Mar 19 00:03:10 2026
$end
$version
	Icarus Verilog
$end
$timescale
	1ps
$end
$scope module riscv_testbench $end
$var wire 4 ! mem_wmask [3:0] $end
$var wire 32 " mem_wdata [31:0] $end
$var wire 1 # mem_rstrb $end
$var wire 32 $ mem_addr [31:0] $end
$var reg 1 % clk $end
$var reg 32 & mem_rdata [31:0] $end
$var reg 1 ' reset $end
$scope module dut $end
$var wire 1 % clk $end
$var wire 32 ( inst [31:0] $end
$var wire 1 ) mem_rbusy $end
$var wire 32 * mem_rdata [31:0] $end
$var wire 1 # mem_rstrb $end
$var wire 1 + mem_wbusy $end
$var wire 32 , mem_wdata [31:0] $end
$var wire 4 - mem_wmask [3:0] $end
$var wire 1 ' reset $end
$var wire 32 . rs2_data [31:0] $end
$var wire 32 / rs1_data [31:0] $end
$var wire 1 0 reg_write_en $end
$var wire 32 1 reg_write_data [31:0] $end
$var wire 32 2 pc [31:0] $end
$var wire 1 3 mem_write_en $end
$var wire 2 4 mem_to_reg_sel [1:0] $end
$var wire 1 5 mem_read_en $end
$var wire 32 6 mem_addr [31:0] $end
$var wire 1 7 jalr_op $end
$var wire 1 8 jal_op $end
$var wire 3 9 imm_type_sel [2:0] $end
$var wire 32 : imm [31:0] $end
$var wire 1 ; branch_cond $end
$var wire 1 < alu_zero_flag $end
$var wire 1 = alu_src_b_sel $end
$var wire 1 > alu_src_a_sel $end
$var wire 32 ? alu_result [31:0] $end
$var wire 5 @ alu_op [4:0] $end
$var wire 1 A alu_lt_flag $end
$var wire 32 B alu_b [31:0] $end
$var wire 32 C alu_a [31:0] $end
$var reg 32 D load_data_extended [31:0] $end
$var reg 4 E wmask [3:0] $end
$scope module alu_inst $end
$var wire 32 F a [31:0] $end
$var wire 32 G b [31:0] $end
$var wire 5 H alu_op [4:0] $end
$var parameter 5 I ALU_ADD $end
$var parameter 5 J ALU_AND $end
$var parameter 5 K ALU_OR $end
$var parameter 5 L ALU_SLL $end
$var parameter 5 M ALU_SLT $end
$var parameter 5 N ALU_SLTU $end
$var parameter 5 O ALU_SRA $end
$var parameter 5 P ALU_SRL $end
$var parameter 5 Q ALU_SUB $end
$var parameter 5 R ALU_XOR $end
$var reg 32 S result [31:0] $end
$var reg 1 < zero_flag $end
$upscope $end
$scope module cu_inst $end
$var wire 1 A alu_lt_flag $end
$var wire 3 T funct3 [2:0] $end
$var wire 7 U funct7 [6:0] $end
$var wire 7 V opcode [6:0] $end
$var wire 1 < zero_flag $end
$var parameter 5 W ALU_ADD $end
$var parameter 5 X ALU_AND $end
$var parameter 5 Y ALU_OR $end
$var parameter 5 Z ALU_SLL $end
$var parameter 5 [ ALU_SLT $end
$var parameter 5 \ ALU_SLTU $end
$var parameter 5 ] ALU_SRA $end
$var parameter 5 ^ ALU_SRL $end
$var parameter 5 _ ALU_SUB $end
$var parameter 5 ` ALU_XOR $end
$var parameter 7 a AUIPC $end
$var parameter 7 b B_TYPE $end
$var parameter 3 c IMM_B_TYPE $end
$var parameter 3 d IMM_I_TYPE $end
$var parameter 3 e IMM_J_TYPE $end
$var parameter 1 f IMM_SEL $end
$var parameter 3 g IMM_S_TYPE $end
$var parameter 3 h IMM_U_TYPE $end
$var parameter 7 i I_TYPE_A $end
$var parameter 7 j I_TYPE_J $end
$var parameter 7 k I_TYPE_L $end
$var parameter 7 l JAL $end
$var parameter 7 m LUI $end
$var parameter 2 n MTR_ALU_RES $end
$var parameter 2 o MTR_MEM_DATA $end
$var parameter 2 p MTR_PC_4 $end
$var parameter 1 q PC_SEL $end
$var parameter 1 r RS1_SEL $end
$var parameter 1 s RS2_SEL $end
$var parameter 7 t R_TYPE $end
$var parameter 7 u S_TYPE $end
$var reg 5 v alu_op [4:0] $end
$var reg 1 > alu_src_a_sel $end
$var reg 1 = alu_src_b_sel $end
$var reg 1 ; branch_cond $end
$var reg 3 w imm_type_sel [2:0] $end
$var reg 1 8 jal_op $end
$var reg 1 7 jalr_op $end
$var reg 1 5 mem_read_en $end
$var reg 2 x mem_to_reg_sel [1:0] $end
$var reg 1 3 mem_write_en $end
$var reg 1 0 reg_write_en $end
$upscope $end
$scope module ig_inst $end
$var wire 3 y imm_type_sel [2:0] $end
$var wire 32 z inst [31:0] $end
$var parameter 3 { IMM_B_TYPE $end
$var parameter 3 | IMM_I_TYPE $end
$var parameter 3 } IMM_J_TYPE $end
$var parameter 3 ~ IMM_S_TYPE $end
$var parameter 3 !" IMM_U_TYPE $end
$var reg 32 "" imm [31:0] $end
$upscope $end
$scope module pc_logic_inst $end
$var wire 1 ; branch_cond $end
$var wire 1 % clk $end
$var wire 32 #" imm [31:0] $end
$var wire 1 8 jal_op $end
$var wire 1 7 jalr_op $end
$var wire 1 ' reset $end
$var wire 32 $" rs1_data [31:0] $end
$var reg 32 %" next_pc [31:0] $end
$var reg 32 &" pc [31:0] $end
$upscope $end
$scope module rf_inst $end
$var wire 1 % clk $end
$var wire 5 '" rd_addr [4:0] $end
$var wire 5 (" rs1_addr [4:0] $end
$var wire 5 )" rs2_addr [4:0] $end
$var wire 32 *" write_data [31:0] $end
$var wire 1 0 write_enable $end
$var wire 32 +" rs2_data [31:0] $end
$var wire 32 ," rs1_data [31:0] $end
$var integer 32 -" i [31:0] $end
$upscope $end
$upscope $end
$upscope $end
$enddefinitions $end
$comment Show the parameter values. $end
$dumpall
b11 !"
b1 ~
b100 }
b0 |
b10 {
b100011 u
b110011 t
0s
0r
1q
b10 p
b1 o
b0 n
b110111 m
b1101111 l
b11 k
b1100111 j
b10011 i
b11 h
b1 g
1f
b100 e
b0 d
b10 c
b1100011 b
b10111 a
b101 `
b1 _
b110 ^
b111 ]
b100 \
b11 [
b10 Z
b1000 Y
b1001 X
b0 W
b101 R
b1 Q
b110 P
b111 O
b100 N
b11 M
b10 L
b1000 K
b1001 J
b0 I
$end
#0
$dumpvars
b100000 -"
bx ,"
bx +"
bx *"
bx )"
bx ("
bx '"
bx &"
bx %"
bx $"
bx #"
bx ""
bx z
bx y
bx x
bx w
bx v
bx V
bx U
bx T
bx S
bx H
bx G
bx F
bx E
bx D
bx C
bx B
xA
bx @
bx ?
x>
x=
x<
x;
bx :
bx 9
x8
x7
bx 6
x5
bx 4
x3
bx 2
bx 1
x0
bx /
bx .
bx -
bx ,
z+
bx *
z)
bx (
1'
bx &
0%
bx $
x#
bx "
bx !
$end
#5000
b100 %"
b0 2
b0 &"
1%
#10000
0%
0'
#15000
b1000 %"
b100 2
b100 &"
1%
#20000
0%
#25000
b1100 %"
b1000 2
b1000 &"
1%
#30000
0%
#35000
b10000 %"
b1100 2
b1100 &"
1%
#40000
0%
#45000
b10100 %"
b10000 2
b10000 &"
1%
#50000
0%
#55000
b11000 %"
b10100 2
b10100 &"
1%
#60000
0%
#65000
b11100 %"
b11000 2
b11000 &"
1%
#70000
0%
#75000
b100000 %"
b11100 2
b11100 &"
1%
#80000
0%
#85000
b100100 %"
b100000 2
b100000 &"
1%
#90000
0%
#95000
b101000 %"
b100100 2
b100100 &"
1%
#100000
0%
#105000
b101100 %"
b101000 2
b101000 &"
1%
